vdown/__init__.py
vdown/cmd.py
vdown/down.py
vdown/m3u8.py
vdown/util.py
vdown/youtube.py
vdown-0.1.1.dist-info/METADATA
vdown-0.1.1.dist-info/WHEEL
vdown-0.1.1.dist-info/entry_points.txt
vdown-0.1.1.dist-info/top_level.txt
vdown-0.1.1.dist-info/RECORD
