Metadata-Version: 2.1
Name: vdown
Version: 0.1.1
Summary: A tool for download m3u8/youtube videos.
Home-page: https://github.com/drunkdream/video-downloader
Author: drunkdream
Author-email: drunkdream@qq.com
License: MIT
Platform: UNKNOWN
Classifier: Development Status :: 3 - Alpha
Classifier: License :: OSI Approved :: MIT License
Classifier: Programming Language :: Python
Classifier: Programming Language :: Python :: 3.5
Classifier: Programming Language :: Python :: 3.6
Classifier: Intended Audience :: Developers
Requires-Python: >=3.5
Requires-Dist: aiohttp
Requires-Dist: bs4
